phyre/__init__.py
phyre/action_mappers.py
phyre/action_simulator.py
phyre/check_solutions.py
phyre/compute_solution_power.py
phyre/diversity.py
phyre/eval_task_complexity.py
phyre/generate_tasks.py
phyre/loader.py
phyre/metrics.py
phyre/objects_util.py
phyre/server.py
phyre/settings.py
phyre/simulation.py
phyre/simulation_cache.py
phyre/simulator.py
phyre/simulator_bindings.cpython-36m-x86_64-linux-gnu.so
phyre/util.py
phyre/virtual_tools.py
phyre/vis.py
phyre/creator/__init__.py
phyre/creator/constants.py
phyre/creator/creator.py
phyre/creator/factories.py
phyre/creator/shapes.py
phyre/data/evaluations/00000.lzma
phyre/data/evaluations/00000.meta.json
phyre/data/evaluations/00001.lzma
phyre/data/evaluations/00001.meta.json
phyre/data/evaluations/00002.lzma
phyre/data/evaluations/00002.meta.json
phyre/data/evaluations/00003.lzma
phyre/data/evaluations/00003.meta.json
phyre/data/evaluations/00004.lzma
phyre/data/evaluations/00004.meta.json
phyre/data/evaluations/00005.lzma
phyre/data/evaluations/00005.meta.json
phyre/data/evaluations/00006.lzma
phyre/data/evaluations/00006.meta.json
phyre/data/evaluations/00007.lzma
phyre/data/evaluations/00007.meta.json
phyre/data/evaluations/00008.lzma
phyre/data/evaluations/00008.meta.json
phyre/data/evaluations/00009.lzma
phyre/data/evaluations/00009.meta.json
phyre/data/evaluations/00010.lzma
phyre/data/evaluations/00010.meta.json
phyre/data/evaluations/00011.lzma
phyre/data/evaluations/00011.meta.json
phyre/data/evaluations/00012.lzma
phyre/data/evaluations/00012.meta.json
phyre/data/evaluations/00013.lzma
phyre/data/evaluations/00013.meta.json
phyre/data/evaluations/00014.lzma
phyre/data/evaluations/00014.meta.json
phyre/data/evaluations/00015.lzma
phyre/data/evaluations/00015.meta.json
phyre/data/evaluations/00016.lzma
phyre/data/evaluations/00016.meta.json
phyre/data/evaluations/00017.lzma
phyre/data/evaluations/00017.meta.json
phyre/data/evaluations/00018.lzma
phyre/data/evaluations/00018.meta.json
phyre-0.2.2.dist-info/LICENSE.txt
phyre-0.2.2.dist-info/METADATA
phyre-0.2.2.dist-info/WHEEL
phyre-0.2.2.dist-info/top_level.txt
phyre-0.2.2.dist-info/RECORD
