Metadata-Version: 2.1
Name: phyre
Version: 0.2.2
Summary: Benchmark for PHYsical REasoning
Home-page: https://phyre.ai
Author: Facebook AI Research
License: Apache Software License
Platform: UNKNOWN
Classifier: Programming Language :: Python :: 3.6
Classifier: License :: OSI Approved :: Apache Software License
Requires-Dist: nose
Requires-Dist: numpy
Requires-Dist: tornado
Requires-Dist: thrift (==0.11.0)
Requires-Dist: imageio
Requires-Dist: scipy
Requires-Dist: joblib
